apprendaapipythonclient/__init__.py
apprendaapipythonclient/api_client.py
apprendaapipythonclient/apprenda_account_client.py
apprendaapipythonclient/apprenda_api_client.py
apprendaapipythonclient/apprenda_developer_client.py
apprendaapipythonclient/apprenda_soc_client.py
apprendaapipythonclient/configuration.py
apprendaapipythonclient/rest.py
apprendaapipythonclient/apis/__init__.py
apprendaapipythonclient/apis/account/__init__.py
apprendaapipythonclient/apis/account/application_versions_api.py
apprendaapipythonclient/apis/account/plans_api.py
apprendaapipythonclient/apis/account/platform_api.py
apprendaapipythonclient/apis/account/roles_api.py
apprendaapipythonclient/apis/account/securables_api.py
apprendaapipythonclient/apis/account/subscriptions_api.py
apprendaapipythonclient/apis/account/upgrade_status_api.py
apprendaapipythonclient/apis/account/users_api.py
apprendaapipythonclient/apis/developer/__init__.py
apprendaapipythonclient/apis/developer/add_ons_api.py
apprendaapipythonclient/apis/developer/apps_api.py
apprendaapipythonclient/apis/developer/cache_nodes_api.py
apprendaapipythonclient/apis/developer/clouds_api.py
apprendaapipythonclient/apis/developer/components_api.py
apprendaapipythonclient/apis/developer/context_api.py
apprendaapipythonclient/apis/developer/custom_properties_api.py
apprendaapipythonclient/apis/developer/custom_url_certificate_api.py
apprendaapipythonclient/apis/developer/environment_variables_api.py
apprendaapipythonclient/apis/developer/groups_api.py
apprendaapipythonclient/apis/developer/java_container_api.py
apprendaapipythonclient/apis/developer/java_runtime_api.py
apprendaapipythonclient/apis/developer/log_overrides_api.py
apprendaapipythonclient/apis/developer/log_summary_api.py
apprendaapipythonclient/apis/developer/monitoring_subscriptions_api.py
apprendaapipythonclient/apis/developer/plans_api.py
apprendaapipythonclient/apis/developer/platform_api.py
apprendaapipythonclient-0.0.12.dist-info/DESCRIPTION.rst
apprendaapipythonclient-0.0.12.dist-info/METADATA
apprendaapipythonclient-0.0.12.dist-info/RECORD
apprendaapipythonclient-0.0.12.dist-info/WHEEL
apprendaapipythonclient-0.0.12.dist-info/metadata.json
apprendaapipythonclient-0.0.12.dist-info/top_level.txt
