Metadata-Version: 2.0
Name: apprendaapipythonclient
Version: 0.0.12
Summary: REST API client for Apprenda APIs
Home-page: https://bitbucket.org/apprenda/apprendaapipythonclient
Author: Mathieson Sterling
Author-email: gsterling@apprenda.com
License: MIT
Keywords: Apprenda api rest development
Platform: UNKNOWN
Classifier: Development Status :: 3 - Alpha
Classifier: Intended Audience :: Developers
Classifier: Topic :: Software Development :: Build Tools
Classifier: License :: OSI Approved :: MIT License
Classifier: Programming Language :: Python :: 2
Classifier: Programming Language :: Python :: 2.7
Classifier: Programming Language :: Python :: 3
Classifier: Programming Language :: Python :: 3.3
Classifier: Programming Language :: Python :: 3.4
Classifier: Programming Language :: Python :: 3.5
Requires-Dist: certifi
Requires-Dist: six
Requires-Dist: urllib3
Provides-Extra: dev
Requires-Dist: check-manifest; extra == 'dev'
Provides-Extra: test
Requires-Dist: coverage; extra == 'test'
